README.md
setup.py
toolkit_w/__init__.py
toolkit_w/version.py
toolkit_w/whatify_toolkit.py
toolkit_w.egg-info/PKG-INFO
toolkit_w.egg-info/SOURCES.txt
toolkit_w.egg-info/dependency_links.txt
toolkit_w.egg-info/requires.txt
toolkit_w.egg-info/top_level.txt
toolkit_w/cleaner/__init__.py
toolkit_w/cleaner/cleaner.py
toolkit_w/crp/__init__.py
toolkit_w/crp/crp.py
toolkit_w/data_source/__init__.py
toolkit_w/snowflake/__init__.py
toolkit_w/snowflake/snowflakeq.py
toolkit_w/tellme/__init__.py
toolkit_w/tellme/app.py
toolkit_w/tellme/dash.py
toolkit_w/tellme/tellme.py