Metadata-Version: 2.1
Name: toolkit-w
Version: 0.0.170
Summary: Python client for Whathif API
Home-page: UNKNOWN
Author: Whatify
License: UNKNOWN
Platform: any
Classifier: Development Status :: 4 - Beta
Classifier: Environment :: Console
Classifier: Intended Audience :: Developers
Classifier: License :: OSI Approved :: MIT License
